zc/table/README.rst
zc/table/TODO.txt
zc/table/__init__.py
zc/table/batching.pt
zc/table/batching.py
zc/table/column.py
zc/table/column.rst
zc/table/configure.zcml
zc/table/fieldcolumn.py
zc/table/fieldcolumn.rst
zc/table/interfaces.py
zc/table/table.py
zc/table/testing.py
zc/table/tests.py
zc/table/resources/sort_arrows.gif
zc/table/resources/sort_arrows_down.gif
zc/table/resources/sort_arrows_up.gif
zc/table/resources/sorting.js
zc_table-2.0.dist-info/licenses/LICENSE.txt
zc_table-2.0.dist-info/METADATA
zc_table-2.0.dist-info/WHEEL
zc_table-2.0.dist-info/top_level.txt
zc_table-2.0.dist-info/RECORD
